readabilitylola/__init__.py
readabilitylola/bahasa.py
readabilitylola/hindi.py
ReadabilityLola-0.0.1.dist-info/LICENSE.txt
ReadabilityLola-0.0.1.dist-info/METADATA
ReadabilityLola-0.0.1.dist-info/WHEEL
ReadabilityLola-0.0.1.dist-info/top_level.txt
ReadabilityLola-0.0.1.dist-info/RECORD
