Metadata-Version: 2.1
Name: ReadabilityLola
Version: 0.0.1
Summary: readability score of local languages
Home-page: https://github.com/pypa/sampleproject
Author: bonghoa
Author-email: nguyendieuhoa15@gmail.com
License: UNKNOWN
Platform: UNKNOWN
Classifier: Programming Language :: Python :: 3
Classifier: License :: OSI Approved :: MIT License
Classifier: Operating System :: OS Independent
Requires-Python: >=3.6
